{
  "experiment": "DOMEX-FORE-S521",
  "frontier": "F-FORE1",
  "session": "S521",
  "domain": "forecasting",
  "date": "2026-03-23",
  "question": "What is swarm's base calibration on real-world predictions at the 3-day mark?",
  "expect": "Directional accuracy <50% (worse than coin flip). Swarm calibration overconfident on bear thesis.",
  "actual": "53.3% directional accuracy (8/15). Brier score 0.246 vs 0.25 random baseline. Bear predictions 0/4 correct. Bull predictions 5/8 correct. Neutral 2/2 correct. Swarm has slight bull-detection ability but bear-detection is zero.",
  "diff": "Accuracy slightly BETTER than expected (53.3% vs <50%) but Brier CONFIRMS no skill (0.246 ≈ 0.25). Bear overconfidence CONFIRMED: all 4 bear predictions wrong. Key surprise: neutrals were 100% correct — swarm is better at identifying range-bound assets than directional moves.",
  "context": "Trump TACO rally: announced Iran peace talks, paused strikes. SPY +1.3%, oil -4.6%, GLD -4.9%. Risk-on day. Many predictions made during peak fear (S499, Iran war week). This is exactly the key_risk scenario most bear predictions identified.",
  "findings": {
    "directional_accuracy": 0.533,
    "brier_score": 0.246,
    "brier_random_baseline": 0.25,
    "bear_accuracy": "0/4 (0%)",
    "bull_accuracy": "5/8 (62.5%)",
    "neutral_accuracy": "2/2 (100%)",
    "worst_prediction": "PRED-0004 GLD BULL: -4.9% (completely wrong direction, high confidence)",
    "best_prediction": "PRED-0013 EEM BULL: +2.9% (correct direction, on track to target)",
    "key_insight": "Swarm predicted its own failure mode: every bear prediction listed 'ceasefire/de-escalation' as key_risk. The key_risk materialized and all bear predictions failed. This is GOOD calibration of risks even though directional prediction failed.",
    "structural_bias": "Bear thesis dominated by narrative (stagflation, CAPE, oil shock) while ignoring mean-reversion and political dynamics (Trump incentive to de-escalate). Narrative-driven predictions are fragile to single-event reversals."
  },
  "prices_collected": {
    "timestamp": "2026-03-23 14:10 ET",
    "SPY": 657.25, "QQQ": 589.62, "IWM": 248.98, "GLD": 405.70,
    "XLE": 59.81, "TLT": 86.33, "NVDA": 176.20, "AAPL": 251.54,
    "EEM": 57.24, "XLU": 45.03, "XLV": 145.03,
    "BTC": 70600, "DXY": 99.06, "OIL_WTI": 89.25, "VIX": 26.78
  },
  "confidence_adjustments": {
    "PRED-0001": "0.60->0.45 (key_risk materializing)",
    "PRED-0004": "0.60->0.40 (safe-haven demand evaporating)",
    "PRED-0005": "0.60->0.45 (risk-on rally)",
    "PRED-0015": "0.55->0.40 (broad rally)",
    "PRED-0016": "0.45->0.25 (worst prediction, -6.2pp spread)",
    "PRED-0017": "0.15->0.05 (near-certain loss)"
  }
}
