{
  "schema": "experiment-v2",
  "id": "swarm-combiner-self-merge-s518",
  "session": "S518",
  "lane": "DOMEX-MERGE-S518",
  "frontier": "F-MERGE1",
  "hypothesis": "swarm_combiner.py can execute all 5 merge phases and produce viable output",
  "pre_registered": true,
  "expect": "Self-merge produces INBREEDING zone, 100% convergence, 0 contradictions, single identity",
  "actual": "Self-merge: distance=0.000, INBREEDING zone, 1202L deduplicated, 100% convergence, 0 contradictions, single identity type, 20 CONTEXT_DEPENDENT lessons (same-ID pairs with moderate title overlap)",
  "diff": "20 lessons classified CONTEXT_DEPENDENT rather than COMPATIBLE — classifier is conservative on moderate-overlap titles even for identical content. Expected 0 for self-merge.",
  "outcome": "CONFIRMED",
  "effect_size": "Phase 0-4 gap closed: from 1 tool (compatibility only) to end-to-end merge",
  "lesson": "L-1440",
  "artifacts": ["tools/swarm_combiner.py"],
  "timestamp": "2026-03-23T00:00:00Z"
}
